tests
tornado_redis_sentinel
