Metadata-Version: 1.1
Name: tornado-redis-sentinel
Version: 0.1.2
Summary: Tornado redis library based in toredis that supports sentinel connections.
Home-page: UNKNOWN
Author: Globo.com
Author-email: timehome@corp.globo.com
License: MIT
Keywords: tornado redis sentinel
Platform: UNKNOWN
Classifier: Development Status :: 4 - Beta
Classifier: Intended Audience :: Developers
Classifier: License :: OSI Approved :: MIT License
Classifier: Natural Language :: English
Classifier: Operating System :: MacOS
Classifier: Operating System :: POSIX
Classifier: Operating System :: Unix
Classifier: Operating System :: OS Independent
Classifier: Programming Language :: Python :: 2.7
